django_xhtml2pdf_plus/__init__.py
django_xhtml2pdf_plus/views.py
django_xhtml2pdf_plus-0.1.0.dist-info/LICENSE
django_xhtml2pdf_plus-0.1.0.dist-info/METADATA
django_xhtml2pdf_plus-0.1.0.dist-info/WHEEL
django_xhtml2pdf_plus-0.1.0.dist-info/top_level.txt
django_xhtml2pdf_plus-0.1.0.dist-info/RECORD
